{
  "acorn-bold": 60314,
  "address-book-bold": 59128,
  "address-book-tabs-bold": 61006,
  "air-traffic-control-bold": 60632,
  "airplane-bold": 57346,
  "airplane-in-flight-bold": 58622,
  "airplane-landing-bold": 58626,
  "airplane-takeoff-bold": 58628,
  "airplane-taxiing-bold": 58624,
  "airplane-tilt-bold": 58838,
  "airplay-bold": 57348,
  "alarm-bold": 57350,
  "alien-bold": 59558,
  "align-bottom-bold": 58630,
  "align-bottom-simple-bold": 60172,
  "align-center-horizontal-bold": 58634,
  "align-center-horizontal-simple-bold": 60174,
  "align-center-vertical-bold": 58636,
  "align-center-vertical-simple-bold": 60176,
  "align-left-bold": 58638,
  "align-left-simple-bold": 60142,
  "align-right-bold": 58640,
  "align-right-simple-bold": 60178,
  "align-top-bold": 58642,
  "align-top-simple-bold": 60180,
  "amazon-logo-bold": 59756,
  "ambulance-bold": 58738,
  "anchor-bold": 58644,
  "anchor-simple-bold": 58840,
  "android-logo-bold": 57352,
  "angle-bold": 59324,
  "angular-logo-bold": 60288,
  "aperture-bold": 57354,
  "app-store-logo-bold": 59764,
  "app-window-bold": 58842,
  "apple-logo-bold": 58646,
  "apple-podcasts-logo-bold": 60310,
  "approximate-equals-bold": 60842,
  "archive-bold": 57356,
  "armchair-bold": 57362,
  "arrow-arc-left-bold": 57364,
  "arrow-arc-right-bold": 57366,
  "arrow-bend-double-up-left-bold": 57402,
  "arrow-bend-double-up-right-bold": 57404,
  "arrow-bend-down-left-bold": 57368,
  "arrow-bend-down-right-bold": 57370,
  "arrow-bend-left-down-bold": 57372,
  "arrow-bend-left-up-bold": 57374,
  "arrow-bend-right-down-bold": 57376,
  "arrow-bend-right-up-bold": 57378,
  "arrow-bend-up-left-bold": 57380,
  "arrow-bend-up-right-bold": 57382,
  "arrow-circle-down-bold": 57384,
  "arrow-circle-down-left-bold": 57386,
  "arrow-circle-down-right-bold": 57388,
  "arrow-circle-left-bold": 57434,
  "arrow-circle-right-bold": 57390,
  "arrow-circle-up-bold": 57392,
  "arrow-circle-up-left-bold": 57394,
  "arrow-circle-up-right-bold": 57396,
  "arrow-clockwise-bold": 57398,
  "arrow-counter-clockwise-bold": 57400,
  "arrow-down-bold": 57406,
  "arrow-down-left-bold": 57408,
  "arrow-down-right-bold": 57410,
  "arrow-elbow-down-left-bold": 57412,
  "arrow-elbow-down-right-bold": 57414,
  "arrow-elbow-left-bold": 57416,
  "arrow-elbow-left-down-bold": 57418,
  "arrow-elbow-left-up-bold": 57420,
  "arrow-elbow-right-bold": 57422,
  "arrow-elbow-right-down-bold": 57424,
  "arrow-elbow-right-up-bold": 57426,
  "arrow-elbow-up-left-bold": 57428,
  "arrow-elbow-up-right-bold": 57430,
  "arrow-fat-down-bold": 58648,
  "arrow-fat-left-bold": 58650,
  "arrow-fat-line-down-bold": 58652,
  "arrow-fat-line-left-bold": 58654,
  "arrow-fat-line-right-bold": 58656,
  "arrow-fat-line-up-bold": 58658,
  "arrow-fat-lines-down-bold": 58660,
  "arrow-fat-lines-left-bold": 58662,
  "arrow-fat-lines-right-bold": 58664,
  "arrow-fat-lines-up-bold": 58666,
  "arrow-fat-right-bold": 58668,
  "arrow-fat-up-bold": 58670,
  "arrow-left-bold": 57432,
  "arrow-line-down-bold": 57436,
  "arrow-line-down-left-bold": 57438,
  "arrow-line-down-right-bold": 57440,
  "arrow-line-left-bold": 57442,
  "arrow-line-right-bold": 57444,
  "arrow-line-up-bold": 57446,
  "arrow-line-up-left-bold": 57448,
  "arrow-line-up-right-bold": 57450,
  "arrow-right-bold": 57452,
  "arrow-square-down-bold": 57454,
  "arrow-square-down-left-bold": 57456,
  "arrow-square-down-right-bold": 57458,
  "arrow-square-in-bold": 58844,
  "arrow-square-left-bold": 57460,
  "arrow-square-out-bold": 58846,
  "arrow-square-right-bold": 57462,
  "arrow-square-up-bold": 57464,
  "arrow-square-up-left-bold": 57466,
  "arrow-square-up-right-bold": 57468,
  "arrow-u-down-left-bold": 57470,
  "arrow-u-down-right-bold": 57472,
  "arrow-u-left-down-bold": 57474,
  "arrow-u-left-up-bold": 57476,
  "arrow-u-right-down-bold": 57478,
  "arrow-u-right-up-bold": 57480,
  "arrow-u-up-left-bold": 57482,
  "arrow-u-up-right-bold": 57484,
  "arrow-up-bold": 57486,
  "arrow-up-left-bold": 57488,
  "arrow-up-right-bold": 57490,
  "arrows-clockwise-bold": 57492,
  "arrows-counter-clockwise-bold": 57494,
  "arrows-down-up-bold": 57496,
  "arrows-horizontal-bold": 60166,
  "arrows-in-bold": 57498,
  "arrows-in-cardinal-bold": 57500,
  "arrows-in-line-horizontal-bold": 58672,
  "arrows-in-line-vertical-bold": 58674,
  "arrows-in-simple-bold": 57502,
  "arrows-left-right-bold": 57504,
  "arrows-merge-bold": 60734,
  "arrows-out-bold": 57506,
  "arrows-out-cardinal-bold": 57508,
  "arrows-out-line-horizontal-bold": 58676,
  "arrows-out-line-vertical-bold": 58678,
  "arrows-out-simple-bold": 57510,
  "arrows-split-bold": 60732,
  "arrows-vertical-bold": 60164,
  "article-bold": 57512,
  "article-medium-bold": 58848,
  "article-ny-times-bold": 58850,
  "asclepius-bold, caduceus-bold": 60980,
  "asterisk-bold": 57514,
  "asterisk-simple-bold": 59442,
  "at-bold": 57516,
  "atom-bold": 58852,
  "avocado-bold": 60932,
  "axe-bold": 59900,
  "baby-bold": 59252,
  "baby-carriage-bold": 59416,
  "backpack-bold": 59682,
  "backspace-bold": 57518,
  "bag-bold": 57520,
  "bag-simple-bold": 58854,
  "balloon-bold": 59244,
  "bandaids-bold": 57522,
  "bank-bold": 57524,
  "barbell-bold": 57526,
  "barcode-bold": 57528,
  "barn-bold": 60530,
  "barricade-bold": 59720,
  "baseball-bold": 59162,
  "baseball-cap-bold": 59944,
  "baseball-helmet-bold": 61002,
  "basket-bold": 59748,
  "basketball-bold": 59172,
  "bathtub-bold": 59422,
  "battery-charging-bold": 57530,
  "battery-charging-vertical-bold": 57532,
  "battery-empty-bold": 57534,
  "battery-full-bold": 57536,
  "battery-high-bold": 57538,
  "battery-low-bold": 57540,
  "battery-medium-bold": 57542,
  "battery-plus-bold": 59400,
  "battery-plus-vertical-bold": 60496,
  "battery-vertical-empty-bold": 59334,
  "battery-vertical-full-bold": 59332,
  "battery-vertical-high-bold": 59330,
  "battery-vertical-low-bold": 59326,
  "battery-vertical-medium-bold": 59328,
  "battery-warning-bold": 57544,
  "battery-warning-vertical-bold": 57546,
  "beach-ball-bold": 60708,
  "beanie-bold": 59946,
  "bed-bold": 57548,
  "beer-bottle-bold": 59312,
  "beer-stein-bold": 60258,
  "behance-logo-bold": 59380,
  "bell-bold": 57550,
  "bell-ringing-bold": 58856,
  "bell-simple-bold": 57552,
  "bell-simple-ringing-bold": 58858,
  "bell-simple-slash-bold": 57554,
  "bell-simple-z-bold": 58860,
  "bell-slash-bold": 57556,
  "bell-z-bold": 58862,
  "belt-bold": 59948,
  "bezier-curve-bold": 60160,
  "bicycle-bold": 57558,
  "binary-bold": 61024,
  "binoculars-bold": 60004,
  "biohazard-bold": 59872,
  "bird-bold": 59180,
  "blueprint-bold": 60832,
  "bluetooth-bold": 57562,
  "bluetooth-connected-bold": 57564,
  "bluetooth-slash-bold": 57566,
  "bluetooth-x-bold": 57568,
  "boat-bold": 59270,
  "bomb-bold": 60938,
  "bone-bold": 59378,
  "book-bold": 57570,
  "book-bookmark-bold": 57572,
  "book-open-bold": 57574,
  "book-open-text-bold": 59634,
  "book-open-user-bold": 60896,
  "bookmark-bold": 57576,
  "bookmark-simple-bold": 57578,
  "bookmarks-bold": 57580,
  "bookmarks-simple-bold": 58864,
  "books-bold": 59224,
  "boot-bold": 60618,
  "boules-bold": 59170,
  "bounding-box-bold": 59086,
  "bowl-food-bold": 60068,
  "bowl-steam-bold": 59620,
  "bowling-ball-bold": 59956,
  "box-arrow-down-bold, archive-box-bold": 57358,
  "box-arrow-up-bold": 61012,
  "boxing-glove-bold": 59958,
  "brackets-angle-bold": 59490,
  "brackets-curly-bold": 59488,
  "brackets-round-bold": 59492,
  "brackets-square-bold": 59486,
  "brain-bold": 59214,
  "brandy-bold": 59060,
  "bread-bold": 59420,
  "bridge-bold": 60008,
  "briefcase-bold": 57582,
  "briefcase-metal-bold": 58866,
  "broadcast-bold": 57586,
  "broom-bold": 60500,
  "browser-bold": 57588,
  "browsers-bold": 57590,
  "bug-bold": 58868,
  "bug-beetle-bold": 58870,
  "bug-droid-bold": 58872,
  "building-bold": 57600,
  "building-apartment-bold": 57598,
  "building-office-bold": 57599,
  "buildings-bold": 57602,
  "bulldozer-bold": 60524,
  "bus-bold": 57606,
  "butterfly-bold": 60014,
  "cable-car-bold": 58524,
  "cactus-bold": 59672,
  "cake-bold": 59264,
  "calculator-bold": 58680,
  "calendar-bold": 57608,
  "calendar-blank-bold": 57610,
  "calendar-check-bold": 59154,
  "calendar-dot-bold": 59314,
  "calendar-dots-bold": 59316,
  "calendar-heart-bold": 59568,
  "calendar-minus-bold": 59924,
  "calendar-plus-bold": 59156,
  "calendar-slash-bold": 59922,
  "calendar-star-bold": 59570,
  "calendar-x-bold": 57612,
  "call-bell-bold": 59358,
  "camera-bold": 57614,
  "camera-plus-bold": 60504,
  "camera-rotate-bold": 59300,
  "camera-slash-bold": 57616,
  "campfire-bold": 59864,
  "car-bold": 57618,
  "car-battery-bold": 60976,
  "car-profile-bold": 59596,
  "car-simple-bold": 57620,
  "cardholder-bold": 58874,
  "cards-bold": 57592,
  "cards-three-bold": 61008,
  "caret-circle-double-down-bold": 57622,
  "caret-circle-double-left-bold": 57624,
  "caret-circle-double-right-bold": 57626,
  "caret-circle-double-up-bold": 57628,
  "caret-circle-down-bold": 57630,
  "caret-circle-left-bold": 57632,
  "caret-circle-right-bold": 57634,
  "caret-circle-up-bold": 57636,
  "caret-circle-up-down-bold": 57662,
  "caret-double-down-bold": 57638,
  "caret-double-left-bold": 57640,
  "caret-double-right-bold": 57642,
  "caret-double-up-bold": 57644,
  "caret-down-bold": 57654,
  "caret-left-bold": 57656,
  "caret-line-down-bold": 57652,
  "caret-line-left-bold": 57650,
  "caret-line-right-bold": 57648,
  "caret-line-up-bold": 57646,
  "caret-right-bold": 57658,
  "caret-up-bold": 57660,
  "caret-up-down-bold": 57664,
  "carrot-bold": 60728,
  "cash-register-bold": 60800,
  "cassette-tape-bold": 60718,
  "castle-turret-bold": 59856,
  "cat-bold": 59208,
  "cell-signal-full-bold": 57666,
  "cell-signal-high-bold": 57668,
  "cell-signal-low-bold": 57670,
  "cell-signal-medium-bold": 57672,
  "cell-signal-none-bold": 57674,
  "cell-signal-slash-bold": 57676,
  "cell-signal-x-bold": 57678,
  "cell-tower-bold": 60330,
  "certificate-bold": 59238,
  "chair-bold": 59728,
  "chalkboard-bold": 58876,
  "chalkboard-simple-bold": 58878,
  "chalkboard-teacher-bold": 58880,
  "champagne-bold": 60106,
  "charging-station-bold": 59600,
  "chart-bar-bold": 57680,
  "chart-bar-horizontal-bold": 57682,
  "chart-donut-bold": 60070,
  "chart-line-bold": 57684,
  "chart-line-down-bold": 59574,
  "chart-line-up-bold": 57686,
  "chart-pie-bold": 57688,
  "chart-pie-slice-bold": 57690,
  "chart-polar-bold": 60072,
  "chart-scatter-bold": 60076,
  "chat-bold": 57692,
  "chat-centered-bold": 57696,
  "chat-centered-dots-bold": 57700,
  "chat-centered-slash-bold": 57698,
  "chat-centered-text-bold": 57702,
  "chat-circle-bold": 57704,
  "chat-circle-dots-bold": 57708,
  "chat-circle-slash-bold": 57706,
  "chat-circle-text-bold": 57710,
  "chat-dots-bold": 57712,
  "chat-slash-bold": 57694,
  "chat-teardrop-bold": 57714,
  "chat-teardrop-dots-bold": 57718,
  "chat-teardrop-slash-bold": 57716,
  "chat-teardrop-text-bold": 57720,
  "chat-text-bold": 57722,
  "chats-bold": 57724,
  "chats-circle-bold": 57726,
  "chats-teardrop-bold": 57728,
  "check-bold": 57730,
  "check-circle-bold": 57732,
  "check-fat-bold": 60326,
  "check-square-bold": 57734,
  "check-square-offset-bold": 57736,
  "checkerboard-bold": 59588,
  "checks-bold": 58682,
  "cheers-bold": 59978,
  "cheese-bold": 59902,
  "chef-hat-bold": 60814,
  "cherries-bold": 59440,
  "church-bold": 60650,
  "cigarette-bold": 60816,
  "cigarette-slash-bold": 60818,
  "circle-bold": 57738,
  "circle-dashed-bold": 58882,
  "circle-half-bold": 57740,
  "circle-half-tilt-bold": 57742,
  "circle-notch-bold": 60228,
  "circles-four-bold": 57744,
  "circles-three-bold": 57746,
  "circles-three-plus-bold": 57748,
  "circuitry-bold": 59842,
  "city-bold": 60010,
  "clipboard-bold": 57750,
  "clipboard-text-bold": 57752,
  "clock-bold": 57754,
  "clock-afternoon-bold": 57756,
  "clock-clockwise-bold": 57758,
  "clock-countdown-bold": 60716,
  "clock-counter-clockwise-bold": 57760,
  "clock-user-bold": 60908,
  "closed-captioning-bold": 57764,
  "cloud-bold": 57770,
  "cloud-arrow-down-bold": 57772,
  "cloud-arrow-up-bold": 57774,
  "cloud-check-bold": 57776,
  "cloud-fog-bold": 58684,
  "cloud-lightning-bold": 57778,
  "cloud-moon-bold": 58686,
  "cloud-rain-bold": 57780,
  "cloud-slash-bold": 57782,
  "cloud-snow-bold": 57784,
  "cloud-sun-bold": 58688,
  "cloud-warning-bold": 60056,
  "cloud-x-bold": 60054,
  "clover-bold": 60872,
  "club-bold": 57786,
  "coat-hanger-bold": 59390,
  "coda-logo-bold": 59342,
  "code-bold": 57788,
  "code-block-bold": 60158,
  "code-simple-bold": 57790,
  "codepen-logo-bold": 59768,
  "codesandbox-logo-bold": 59910,
  "coffee-bold": 57794,
  "coffee-bean-bold": 57792,
  "coin-bold": 58894,
  "coin-vertical-bold": 60232,
  "coins-bold": 59278,
  "columns-bold": 58694,
  "columns-plus-left-bold": 58692,
  "columns-plus-right-bold": 58690,
  "command-bold": 57796,
  "compass-bold": 57800,
  "compass-rose-bold": 57798,
  "compass-tool-bold": 59918,
  "computer-tower-bold": 58696,
  "confetti-bold": 59418,
  "contactless-payment-bold": 60738,
  "control-bold": 60582,
  "cookie-bold": 59082,
  "cooking-pot-bold": 59236,
  "copy-bold": 57802,
  "copy-simple-bold": 57804,
  "copyleft-bold": 59498,
  "copyright-bold": 58698,
  "corners-in-bold": 57806,
  "corners-out-bold": 57808,
  "couch-bold": 59382,
  "court-basketball-bold": 60982,
  "cow-bold": 60094,
  "cowboy-hat-bold": 60690,
  "cpu-bold": 58896,
  "crane-bold": 60744,
  "crane-tower-bold": 60745,
  "credit-card-bold": 57810,
  "cricket-bold": 60946,
  "crop-bold": 57812,
  "cross-bold": 59552,
  "crosshair-bold": 57814,
  "crosshair-simple-bold": 57816,
  "crown-bold": 58900,
  "crown-cross-bold": 61022,
  "crown-simple-bold": 58902,
  "cube-bold": 57818,
  "cube-focus-bold": 60682,
  "cube-transparent-bold": 60540,
  "currency-btc-bold": 58904,
  "currency-circle-dollar-bold": 58700,
  "currency-cny-bold": 58702,
  "currency-dollar-bold": 58704,
  "currency-dollar-simple-bold": 58706,
  "currency-eth-bold": 60122,
  "currency-eur-bold": 58708,
  "currency-gbp-bold": 58710,
  "currency-inr-bold": 58712,
  "currency-jpy-bold": 58714,
  "currency-krw-bold": 58716,
  "currency-kzt-bold": 60492,
  "currency-ngn-bold": 60242,
  "currency-rub-bold": 58718,
  "cursor-bold": 57820,
  "cursor-click-bold": 59336,
  "cursor-text-bold": 59352,
  "cylinder-bold": 59644,
  "database-bold": 57822,
  "desk-bold": 60694,
  "desktop-bold": 58720,
  "desktop-tower-bold": 58722,
  "detective-bold": 59454,
  "dev-to-logo-bold": 60686,
  "device-mobile-bold": 57824,
  "device-mobile-camera-bold": 57826,
  "device-mobile-slash-bold": 60998,
  "device-mobile-speaker-bold": 57828,
  "device-rotate-bold": 60914,
  "device-tablet-bold": 57830,
  "device-tablet-camera-bold": 57832,
  "device-tablet-speaker-bold": 57834,
  "devices-bold": 60324,
  "diamond-bold": 57836,
  "diamonds-four-bold": 59636,
  "dice-five-bold": 57838,
  "dice-four-bold": 57840,
  "dice-one-bold": 57842,
  "dice-six-bold": 57844,
  "dice-three-bold": 57846,
  "dice-two-bold": 57848,
  "disc-bold": 58724,
  "disco-ball-bold": 60824,
  "discord-logo-bold": 58906,
  "divide-bold": 57850,
  "dna-bold": 59684,
  "dog-bold": 59210,
  "door-bold": 58908,
  "door-open-bold": 59366,
  "dot-bold": 60638,
  "dot-outline-bold": 60640,
  "dots-nine-bold": 57852,
  "dots-six-bold": 59284,
  "dots-six-vertical-bold": 60130,
  "dots-three-bold": 57854,
  "dots-three-circle-bold": 57856,
  "dots-three-circle-vertical-bold": 57858,
  "dots-three-outline-bold": 57860,
  "dots-three-outline-vertical-bold": 57862,
  "dots-three-vertical-bold": 57864,
  "download-bold": 57866,
  "download-simple-bold": 57868,
  "dress-bold": 60030,
  "dresser-bold": 59726,
  "dribbble-logo-bold": 57870,
  "drone-bold": 60788,
  "drop-bold": 57872,
  "drop-half-bold": 58726,
  "drop-half-bottom-bold": 60224,
  "drop-simple-bold": 60978,
  "drop-slash-bold": 59732,
  "dropbox-logo-bold": 59344,
  "ear-bold": 59148,
  "ear-slash-bold": 59150,
  "egg-bold": 59410,
  "egg-crack-bold": 60260,
  "eject-bold": 57874,
  "eject-simple-bold": 59054,
  "elevator-bold": 60608,
  "empty-bold": 60860,
  "engine-bold": 60032,
  "envelope-bold": 57876,
  "envelope-open-bold": 57878,
  "envelope-simple-bold": 57880,
  "envelope-simple-open-bold": 57882,
  "equalizer-bold": 60348,
  "equals-bold": 57884,
  "eraser-bold": 57886,
  "escalator-down-bold": 60602,
  "escalator-up-bold": 60604,
  "exam-bold": 59202,
  "exclamation-mark-bold": 60996,
  "exclude-bold": 59522,
  "exclude-square-bold": 59520,
  "export-bold": 60144,
  "eye-bold": 57888,
  "eye-closed-bold": 57890,
  "eye-slash-bold": 57892,
  "eyedropper-bold": 58728,
  "eyedropper-sample-bold": 60100,
  "eyeglasses-bold": 59322,
  "eyes-bold": 61020,
  "face-mask-bold": 58730,
  "facebook-logo-bold": 57894,
  "factory-bold": 59232,
  "faders-bold": 57896,
  "faders-horizontal-bold": 57898,
  "fallout-shelter-bold": 59870,
  "fan-bold": 59890,
  "farm-bold": 60528,
  "fast-forward-bold": 59046,
  "fast-forward-circle-bold": 57900,
  "feather-bold": 59840,
  "fediverse-logo-bold": 60774,
  "figma-logo-bold": 57902,
  "file-bold": 57904,
  "file-archive-bold": 60202,
  "file-arrow-down-bold": 57906,
  "file-arrow-up-bold": 58910,
  "file-audio-bold": 59936,
  "file-c-bold": 60210,
  "file-c-sharp-bold": 60208,
  "file-cloud-bold": 59742,
  "file-code-bold": 59668,
  "file-cpp-bold": 60206,
  "file-css-bold": 60212,
  "file-csv-bold": 60188,
  "file-dashed-bold, file-dotted-bold": 59140,
  "file-doc-bold": 60190,
  "file-html-bold": 60216,
  "file-image-bold": 59940,
  "file-ini-bold": 60211,
  "file-jpg-bold": 60186,
  "file-js-bold": 60196,
  "file-jsx-bold": 60218,
  "file-lock-bold": 59740,
  "file-magnifying-glass-bold, file-search-bold": 57912,
  "file-md-bold": 60752,
  "file-minus-bold": 57908,
  "file-pdf-bold": 59138,
  "file-plus-bold": 57910,
  "file-png-bold": 60184,
  "file-ppt-bold": 60192,
  "file-py-bold": 60204,
  "file-rs-bold": 60200,
  "file-sql-bold": 60750,
  "file-svg-bold": 60680,
  "file-text-bold": 57914,
  "file-ts-bold": 60198,
  "file-tsx-bold": 60220,
  "file-txt-bold": 60213,
  "file-video-bold": 59938,
  "file-vue-bold": 60222,
  "file-x-bold": 57916,
  "file-xls-bold": 60194,
  "file-zip-bold": 59736,
  "files-bold": 59152,
  "film-reel-bold": 59584,
  "film-script-bold": 60240,
  "film-slate-bold": 59586,
  "film-strip-bold": 59282,
  "fingerprint-bold": 57918,
  "fingerprint-simple-bold": 57920,
  "finn-the-human-bold": 58732,
  "fire-bold": 57922,
  "fire-extinguisher-bold": 59880,
  "fire-simple-bold": 58912,
  "fire-truck-bold": 58740,
  "first-aid-bold": 58734,
  "first-aid-kit-bold": 58736,
  "fish-bold": 59176,
  "fish-simple-bold": 59178,
  "flag-bold": 57924,
  "flag-banner-bold": 58914,
  "flag-banner-fold-bold": 60658,
  "flag-checkered-bold": 59960,
  "flag-pennant-bold": 60656,
  "flame-bold": 58916,
  "flashlight-bold": 57926,
  "flask-bold": 59294,
  "flip-horizontal-bold": 60778,
  "flip-vertical-bold": 60780,
  "floppy-disk-bold": 57928,
  "floppy-disk-back-bold": 60148,
  "flow-arrow-bold": 59116,
  "flower-bold": 59230,
  "flower-lotus-bold": 59084,
  "flower-tulip-bold": 60108,
  "flying-saucer-bold": 60234,
  "folder-bold, folder-notch-bold": 57930,
  "folder-dashed-bold, folder-dotted-bold": 59640,
  "folder-lock-bold": 59964,
  "folder-minus-bold, folder-notch-minus-bold": 57940,
  "folder-open-bold, folder-notch-open-bold": 57942,
  "folder-plus-bold, folder-notch-plus-bold": 57944,
  "folder-simple-bold": 57946,
  "folder-simple-dashed-bold, folder-simple-dotted-bold": 60458,
  "folder-simple-lock-bold": 60254,
  "folder-simple-minus-bold": 57948,
  "folder-simple-plus-bold": 57950,
  "folder-simple-star-bold": 60462,
  "folder-simple-user-bold": 60256,
  "folder-star-bold": 60038,
  "folder-user-bold": 60230,
  "folders-bold": 57952,
  "football-bold": 59160,
  "football-helmet-bold": 61004,
  "footprints-bold": 60040,
  "fork-knife-bold": 57954,
  "four-k-bold": 59996,
  "frame-corners-bold": 58918,
  "framer-logo-bold": 57956,
  "function-bold": 60388,
  "funnel-bold": 57958,
  "funnel-simple-bold": 57960,
  "funnel-simple-x-bold": 57962,
  "funnel-x-bold": 57964,
  "game-controller-bold": 57966,
  "garage-bold": 60630,
  "gas-can-bold": 59598,
  "gas-pump-bold": 59240,
  "gauge-bold": 58920,
  "gavel-bold": 59954,
  "gear-bold": 57968,
  "gear-fine-bold": 59516,
  "gear-six-bold": 57970,
  "gender-female-bold": 59104,
  "gender-intersex-bold": 59110,
  "gender-male-bold": 59106,
  "gender-neuter-bold": 59114,
  "gender-nonbinary-bold": 59108,
  "gender-transgender-bold": 59112,
  "ghost-bold": 58922,
  "gif-bold": 57972,
  "gift-bold": 57974,
  "git-branch-bold": 57976,
  "git-commit-bold": 57978,
  "git-diff-bold": 57980,
  "git-fork-bold": 57982,
  "git-merge-bold": 57984,
  "git-pull-request-bold": 57986,
  "github-logo-bold": 58742,
  "gitlab-logo-bold": 59028,
  "gitlab-logo-simple-bold": 59030,
  "globe-bold": 57992,
  "globe-hemisphere-east-bold": 57994,
  "globe-hemisphere-west-bold": 57996,
  "globe-simple-bold": 57998,
  "globe-simple-x-bold": 57988,
  "globe-stand-bold": 58000,
  "globe-x-bold": 57990,
  "goggles-bold": 60596,
  "golf-bold": 59966,
  "goodreads-logo-bold": 60688,
  "google-cardboard-logo-bold": 59318,
  "google-chrome-logo-bold": 59766,
  "google-drive-logo-bold": 59638,
  "google-logo-bold": 58002,
  "google-photos-logo-bold": 60306,
  "google-play-logo-bold": 58004,
  "google-podcasts-logo-bold": 60308,
  "gps-bold": 60888,
  "gps-fix-bold": 60886,
  "gps-slash-bold": 60884,
  "gradient-bold": 60226,
  "graduation-cap-bold": 58924,
  "grains-bold": 60520,
  "grains-slash-bold": 60522,
  "graph-bold": 60248,
  "graphics-card-bold": 58898,
  "greater-than-bold": 60868,
  "greater-than-or-equal-bold": 60834,
  "grid-four-bold": 58006,
  "grid-nine-bold": 60556,
  "guitar-bold": 60042,
  "hair-dryer-bold": 60006,
  "hamburger-bold": 59280,
  "hammer-bold": 59406,
  "hand-bold": 58008,
  "hand-arrow-down-bold": 59982,
  "hand-arrow-up-bold": 61018,
  "hand-coins-bold": 60044,
  "hand-deposit-bold": 61058,
  "hand-eye-bold": 59980,
  "hand-fist-bold": 58746,
  "hand-grabbing-bold": 58748,
  "hand-heart-bold": 59408,
  "hand-palm-bold": 58750,
  "hand-peace-bold": 59340,
  "hand-pointing-bold": 58010,
  "hand-soap-bold": 58928,
  "hand-swipe-left-bold": 60564,
  "hand-swipe-right-bold": 60562,
  "hand-tap-bold": 60560,
  "hand-waving-bold": 58752,
  "hand-withdraw-bold": 61056,
  "handbag-bold": 58012,
  "handbag-simple-bold": 58926,
  "hands-clapping-bold": 59040,
  "hands-praying-bold": 60616,
  "handshake-bold": 58754,
  "hard-drive-bold": 58014,
  "hard-drives-bold": 58016,
  "hard-hat-bold": 60742,
  "hash-bold": 58018,
  "hash-straight-bold": 58020,
  "head-circuit-bold": 59348,
  "headlights-bold": 59134,
  "headphones-bold": 58022,
  "headset-bold": 58756,
  "heart-bold": 58024,
  "heart-break-bold": 60392,
  "heart-half-bold": 60488,
  "heart-straight-bold": 58026,
  "heart-straight-break-bold": 60312,
  "heartbeat-bold": 58028,
  "hexagon-bold": 58030,
  "high-definition-bold": 60046,
  "high-heel-bold": 59624,
  "highlighter-bold": 60534,
  "highlighter-circle-bold": 58930,
  "hockey-bold": 60550,
  "hoodie-bold": 60624,
  "horse-bold": 58032,
  "hospital-bold": 59460,
  "hourglass-bold": 58034,
  "hourglass-high-bold": 58036,
  "hourglass-low-bold": 58038,
  "hourglass-medium-bold": 58040,
  "hourglass-simple-bold": 58042,
  "hourglass-simple-high-bold": 58044,
  "hourglass-simple-low-bold": 58046,
  "hourglass-simple-medium-bold": 58048,
  "house-bold": 58050,
  "house-line-bold": 58052,
  "house-simple-bold": 58054,
  "hurricane-bold": 59534,
  "ice-cream-bold": 59396,
  "identification-badge-bold": 59126,
  "identification-card-bold": 58056,
  "image-bold": 58058,
  "image-broken-bold": 59304,
  "image-square-bold": 58060,
  "images-bold": 59446,
  "images-square-bold": 59444,
  "infinity-bold, lemniscate-bold": 58932,
  "info-bold": 58062,
  "instagram-logo-bold": 58064,
  "intersect-bold": 58066,
  "intersect-square-bold": 59514,
  "intersect-three-bold": 60612,
  "intersection-bold": 60858,
  "invoice-bold": 60994,
  "island-bold": 60934,
  "jar-bold": 59360,
  "jar-label-bold": 59361,
  "jeep-bold": 58068,
  "joystick-bold": 59998,
  "kanban-bold": 60244,
  "key-bold": 58070,
  "key-return-bold": 59266,
  "keyboard-bold": 58072,
  "keyhole-bold": 60024,
  "knife-bold": 58934,
  "ladder-bold": 59876,
  "ladder-simple-bold": 60454,
  "lamp-bold": 58936,
  "lamp-pendant-bold": 60974,
  "laptop-bold": 58758,
  "lasso-bold": 60870,
  "lastfm-logo-bold": 59458,
  "layout-bold": 59094,
  "leaf-bold": 58074,
  "lectern-bold": 59738,
  "lego-bold": 59590,
  "lego-smiley-bold": 59591,
  "less-than-bold": 60844,
  "less-than-or-equal-bold": 60836,
  "letter-circle-h-bold": 60408,
  "letter-circle-p-bold": 60424,
  "letter-circle-v-bold": 60436,
  "lifebuoy-bold": 58938,
  "lightbulb-bold": 58076,
  "lightbulb-filament-bold": 58940,
  "lighthouse-bold": 59894,
  "lightning-bold": 58078,
  "lightning-a-bold": 60036,
  "lightning-slash-bold": 58080,
  "line-segment-bold": 59090,
  "line-segments-bold": 59092,
  "line-vertical-bold": 60784,
  "link-bold": 58082,
  "link-break-bold": 58084,
  "link-simple-bold": 58086,
  "link-simple-break-bold": 58088,
  "link-simple-horizontal-bold": 58090,
  "link-simple-horizontal-break-bold": 58092,
  "linkedin-logo-bold": 58094,
  "linktree-logo-bold": 60910,
  "linux-logo-bold": 60162,
  "list-bold": 58096,
  "list-bullets-bold": 58098,
  "list-checks-bold": 60124,
  "list-dashes-bold": 58100,
  "list-heart-bold": 60382,
  "list-magnifying-glass-bold": 60384,
  "list-numbers-bold": 58102,
  "list-plus-bold": 58104,
  "list-star-bold": 60380,
  "lock-bold": 58106,
  "lock-key-bold": 58110,
  "lock-key-open-bold": 58112,
  "lock-laminated-bold": 58114,
  "lock-laminated-open-bold": 58116,
  "lock-open-bold": 58118,
  "lock-simple-bold": 58120,
  "lock-simple-open-bold": 58122,
  "lockers-bold": 60600,
  "log-bold": 60802,
  "magic-wand-bold": 59062,
  "magnet-bold": 59008,
  "magnet-straight-bold": 59010,
  "magnifying-glass-bold": 58124,
  "magnifying-glass-minus-bold": 58126,
  "magnifying-glass-plus-bold": 58128,
  "mailbox-bold": 60446,
  "map-pin-bold": 58134,
  "map-pin-area-bold": 60986,
  "map-pin-line-bold": 58136,
  "map-pin-plus-bold": 58132,
  "map-pin-simple-bold": 60990,
  "map-pin-simple-area-bold": 60988,
  "map-pin-simple-line-bold": 60984,
  "map-trifold-bold": 58138,
  "markdown-logo-bold": 58632,
  "marker-circle-bold": 58944,
  "martini-bold": 58140,
  "mask-happy-bold": 59892,
  "mask-sad-bold": 60318,
  "mastodon-logo-bold": 60776,
  "math-operations-bold": 58142,
  "matrix-logo-bold": 60772,
  "medal-bold": 58144,
  "medal-military-bold": 60668,
  "medium-logo-bold": 58146,
  "megaphone-bold": 58148,
  "megaphone-simple-bold": 58946,
  "member-of-bold": 60866,
  "memory-bold": 59844,
  "messenger-logo-bold": 59096,
  "meta-logo-bold": 60674,
  "meteor-bold": 59834,
  "metronome-bold": 60558,
  "microphone-bold": 58150,
  "microphone-slash-bold": 58152,
  "microphone-stage-bold": 59228,
  "microscope-bold": 60538,
  "microsoft-excel-logo-bold": 60268,
  "microsoft-outlook-logo-bold": 60272,
  "microsoft-powerpoint-logo-bold": 60110,
  "microsoft-teams-logo-bold": 60262,
  "microsoft-word-logo-bold": 60266,
  "minus-bold": 58154,
  "minus-circle-bold": 58156,
  "minus-square-bold": 60748,
  "money-bold": 58760,
  "money-wavy-bold": 61032,
  "monitor-bold": 58158,
  "monitor-arrow-up-bold": 58762,
  "monitor-play-bold": 58764,
  "moon-bold": 58160,
  "moon-stars-bold": 58766,
  "moped-bold": 59428,
  "moped-front-bold": 59426,
  "mosque-bold": 60654,
  "motorcycle-bold": 59402,
  "mountains-bold": 59310,
  "mouse-bold": 58170,
  "mouse-left-click-bold": 58164,
  "mouse-middle-click-bold": 58168,
  "mouse-right-click-bold": 58166,
  "mouse-scroll-bold": 58162,
  "mouse-simple-bold": 58948,
  "music-note-bold": 58172,
  "music-note-simple-bold": 58174,
  "music-notes-bold": 58176,
  "music-notes-minus-bold": 60940,
  "music-notes-plus-bold": 60284,
  "music-notes-simple-bold": 58178,
  "navigation-arrow-bold": 60126,
  "needle-bold": 59438,
  "network-bold": 60894,
  "network-slash-bold": 60892,
  "network-x-bold": 60890,
  "newspaper-bold": 58180,
  "newspaper-clipping-bold": 58182,
  "not-equals-bold": 60838,
  "not-member-of-bold": 60846,
  "not-subset-of-bold": 60848,
  "not-superset-of-bold": 60850,
  "notches-bold": 60730,
  "note-bold": 58184,
  "note-blank-bold": 58186,
  "note-pencil-bold": 58188,
  "notebook-bold": 58190,
  "notepad-bold": 58942,
  "notification-bold": 59130,
  "notion-logo-bold": 59808,
  "nuclear-plant-bold": 60796,
  "number-circle-eight-bold": 58194,
  "number-circle-five-bold": 58200,
  "number-circle-four-bold": 58206,
  "number-circle-nine-bold": 58212,
  "number-circle-one-bold": 58218,
  "number-circle-seven-bold": 58224,
  "number-circle-six-bold": 58230,
  "number-circle-three-bold": 58236,
  "number-circle-two-bold": 58242,
  "number-circle-zero-bold": 58248,
  "number-eight-bold": 58192,
  "number-five-bold": 58198,
  "number-four-bold": 58204,
  "number-nine-bold": 58210,
  "number-one-bold": 58216,
  "number-seven-bold": 58222,
  "number-six-bold": 58228,
  "number-square-eight-bold": 58196,
  "number-square-five-bold": 58202,
  "number-square-four-bold": 58208,
  "number-square-nine-bold": 58214,
  "number-square-one-bold": 58220,
  "number-square-seven-bold": 58226,
  "number-square-six-bold": 58232,
  "number-square-three-bold": 58238,
  "number-square-two-bold": 58244,
  "number-square-zero-bold": 58250,
  "number-three-bold": 58234,
  "number-two-bold": 58240,
  "number-zero-bold": 58246,
  "numpad-bold": 58312,
  "nut-bold": 58252,
  "ny-times-logo-bold": 58950,
  "octagon-bold": 58254,
  "office-chair-bold": 59974,
  "onigiri-bold": 60972,
  "open-ai-logo-bold": 59346,
  "option-bold": 59560,
  "orange-bold": 60992,
  "orange-slice-bold": 60726,
  "oven-bold": 60812,
  "package-bold": 58256,
  "paint-brush-bold": 59120,
  "paint-brush-broad-bold": 58768,
  "paint-brush-household-bold": 59122,
  "paint-bucket-bold": 58258,
  "paint-roller-bold": 59124,
  "palette-bold": 59080,
  "panorama-bold": 60066,
  "pants-bold": 60552,
  "paper-plane-bold": 58260,
  "paper-plane-right-bold": 58262,
  "paper-plane-tilt-bold": 58264,
  "paperclip-bold": 58266,
  "paperclip-horizontal-bold": 58770,
  "parachute-bold": 60028,
  "paragraph-bold": 59744,
  "parallelogram-bold": 60614,
  "park-bold": 60594,
  "password-bold": 59218,
  "path-bold": 58268,
  "patreon-logo-bold": 59786,
  "pause-bold": 58270,
  "pause-circle-bold": 58272,
  "paw-print-bold": 58952,
  "paypal-logo-bold": 59788,
  "peace-bold": 58274,
  "pen-bold": 58282,
  "pen-nib-bold": 58284,
  "pen-nib-straight-bold": 58954,
  "pencil-bold": 58286,
  "pencil-circle-bold": 58288,
  "pencil-line-bold": 58290,
  "pencil-ruler-bold": 59654,
  "pencil-simple-bold": 58292,
  "pencil-simple-line-bold": 60358,
  "pencil-simple-slash-bold": 60662,
  "pencil-slash-bold": 60664,
  "pentagon-bold": 60542,
  "pentagram-bold": 60508,
  "pepper-bold": 59722,
  "percent-bold": 58294,
  "person-bold": 58280,
  "person-arms-spread-bold": 60670,
  "person-simple-bold": 59182,
  "person-simple-bike-bold": 59188,
  "person-simple-circle-bold": 61016,
  "person-simple-hike-bold": 60756,
  "person-simple-run-bold": 59184,
  "person-simple-ski-bold": 59164,
  "person-simple-snowboard-bold": 59166,
  "person-simple-swim-bold": 59190,
  "person-simple-tai-chi-bold": 60764,
  "person-simple-throw-bold": 59186,
  "person-simple-walk-bold": 59194,
  "perspective-bold": 60390,
  "phone-bold": 58296,
  "phone-call-bold": 58298,
  "phone-disconnect-bold": 58300,
  "phone-incoming-bold": 58302,
  "phone-list-bold": 58316,
  "phone-outgoing-bold": 58304,
  "phone-pause-bold": 58314,
  "phone-plus-bold": 60502,
  "phone-slash-bold": 58306,
  "phone-transfer-bold": 58310,
  "phone-x-bold": 58308,
  "phosphor-logo-bold": 58318,
  "pi-bold": 60544,
  "piano-keys-bold": 59848,
  "picnic-table-bold": 60966,
  "picture-in-picture-bold": 58956,
  "piggy-bank-bold": 59908,
  "pill-bold": 59136,
  "ping-pong-bold": 59970,
  "pint-glass-bold": 60880,
  "pinterest-logo-bold": 58958,
  "pinwheel-bold": 60316,
  "pipe-bold": 60806,
  "pipe-wrench-bold": 60808,
  "pix-logo-bold": 60610,
  "pizza-bold": 59286,
  "placeholder-bold": 58960,
  "planet-bold": 58962,
  "plant-bold": 60334,
  "play-bold": 58320,
  "play-circle-bold": 58322,
  "play-pause-bold": 59582,
  "playlist-bold": 59050,
  "plug-bold": 59718,
  "plug-charging-bold": 60252,
  "plugs-bold": 60246,
  "plugs-connected-bold": 60250,
  "plus-bold": 58324,
  "plus-circle-bold": 58326,
  "plus-minus-bold": 58328,
  "plus-square-bold": 60746,
  "poker-chip-bold": 58772,
  "police-car-bold": 60490,
  "polygon-bold": 59088,
  "popcorn-bold": 60238,
  "popsicle-bold": 60350,
  "potted-plant-bold": 60450,
  "power-bold": 58330,
  "prescription-bold": 59298,
  "presentation-bold": 58964,
  "presentation-chart-bold": 58966,
  "printer-bold": 58332,
  "prohibit-bold": 58334,
  "prohibit-inset-bold": 58336,
  "projector-screen-bold": 58968,
  "projector-screen-chart-bold": 58970,
  "pulse-bold, activity-bold": 57344,
  "push-pin-bold": 58338,
  "push-pin-simple-bold": 58972,
  "push-pin-simple-slash-bold": 58974,
  "push-pin-slash-bold": 58340,
  "puzzle-piece-bold": 58774,
  "qr-code-bold": 58342,
  "question-bold": 58344,
  "question-mark-bold": 58345,
  "queue-bold": 59052,
  "quotes-bold": 58976,
  "rabbit-bold": 60098,
  "racquet-bold": 60930,
  "radical-bold": 58346,
  "radio-bold": 59262,
  "radio-button-bold": 60168,
  "radioactive-bold": 59868,
  "rainbow-bold": 58776,
  "rainbow-cloud-bold": 58778,
  "ranking-bold": 60770,
  "read-cv-logo-bold": 60684,
  "receipt-bold": 58348,
  "receipt-x-bold": 60736,
  "record-bold": 58350,
  "rectangle-bold": 58352,
  "rectangle-dashed-bold": 58354,
  "recycle-bold": 59226,
  "reddit-logo-bold": 58780,
  "repeat-bold": 58358,
  "repeat-once-bold": 58360,
  "replit-logo-bold": 60298,
  "resize-bold": 60782,
  "rewind-bold": 59048,
  "rewind-circle-bold": 58362,
  "road-horizon-bold": 59448,
  "robot-bold": 59234,
  "rocket-bold": 58364,
  "rocket-launch-bold": 58366,
  "rows-bold": 58786,
  "rows-plus-bottom-bold": 58782,
  "rows-plus-top-bold": 58784,
  "rss-bold": 58368,
  "rss-simple-bold": 58370,
  "rug-bold": 59930,
  "ruler-bold": 59064,
  "sailboat-bold": 59274,
  "scales-bold": 59216,
  "scan-bold": 60342,
  "scan-smiley-bold": 60340,
  "scissors-bold": 60128,
  "scooter-bold": 59424,
  "screencast-bold": 58372,
  "screwdriver-bold": 59502,
  "scribble-bold": 59398,
  "scribble-loop-bold": 58978,
  "scroll-bold": 60282,
  "seal-bold, circle-wavy-bold": 58884,
  "seal-check-bold, circle-wavy-check-bold": 58886,
  "seal-percent-bold": 58890,
  "seal-question-bold, circle-wavy-question-bold": 58888,
  "seal-warning-bold, circle-wavy-warning-bold": 58892,
  "seat-bold": 60302,
  "seatbelt-bold": 60926,
  "security-camera-bold": 60580,
  "selection-bold": 59034,
  "selection-all-bold": 59206,
  "selection-background-bold": 60152,
  "selection-foreground-bold": 60150,
  "selection-inverse-bold": 59204,
  "selection-plus-bold": 59036,
  "selection-slash-bold": 59038,
  "shapes-bold": 60510,
  "share-bold": 58374,
  "share-fat-bold": 60754,
  "share-network-bold": 58376,
  "shield-bold": 58378,
  "shield-check-bold": 58380,
  "shield-checkered-bold": 59144,
  "shield-chevron-bold": 58382,
  "shield-plus-bold": 59142,
  "shield-slash-bold": 58384,
  "shield-star-bold": 60468,
  "shield-warning-bold": 58386,
  "shipping-container-bold": 59276,
  "shirt-folded-bold": 60050,
  "shooting-star-bold": 60666,
  "shopping-bag-bold": 58390,
  "shopping-bag-open-bold": 58392,
  "shopping-cart-bold": 58398,
  "shopping-cart-simple-bold": 58400,
  "shovel-bold": 59878,
  "shower-bold": 59254,
  "shrimp-bold": 60084,
  "shuffle-bold": 58402,
  "shuffle-angular-bold": 58404,
  "shuffle-simple-bold": 58406,
  "sidebar-bold": 60086,
  "sidebar-simple-bold": 60452,
  "sigma-bold": 60088,
  "sign-in-bold": 58408,
  "sign-out-bold": 58410,
  "signature-bold": 60332,
  "signpost-bold": 59548,
  "sim-card-bold": 58980,
  "siren-bold": 59832,
  "sketch-logo-bold": 58412,
  "skip-back-bold": 58788,
  "skip-back-circle-bold": 58414,
  "skip-forward-bold": 58790,
  "skip-forward-circle-bold": 58416,
  "skull-bold": 59670,
  "skype-logo-bold": 59612,
  "slack-logo-bold": 58792,
  "sliders-bold": 58418,
  "sliders-horizontal-bold": 58420,
  "slideshow-bold": 60722,
  "smiley-bold": 58422,
  "smiley-angry-bold": 60514,
  "smiley-blank-bold": 58424,
  "smiley-meh-bold": 58426,
  "smiley-melting-bold": 61014,
  "smiley-nervous-bold": 58428,
  "smiley-sad-bold": 58430,
  "smiley-sticker-bold": 58432,
  "smiley-wink-bold": 58982,
  "smiley-x-eyes-bold": 58434,
  "snapchat-logo-bold": 58984,
  "sneaker-bold": 59404,
  "sneaker-move-bold": 60768,
  "snowflake-bold": 58794,
  "soccer-ball-bold": 59158,
  "sock-bold": 60622,
  "solar-panel-bold": 60794,
  "solar-roof-bold": 60795,
  "sort-ascending-bold": 58436,
  "sort-descending-bold": 58438,
  "soundcloud-logo-bold": 59614,
  "spade-bold": 58440,
  "sparkle-bold": 59042,
  "speaker-hifi-bold": 59912,
  "speaker-high-bold": 58442,
  "speaker-low-bold": 58444,
  "speaker-none-bold": 58446,
  "speaker-simple-high-bold": 58448,
  "speaker-simple-low-bold": 58450,
  "speaker-simple-none-bold": 58452,
  "speaker-simple-slash-bold": 58454,
  "speaker-simple-x-bold": 58456,
  "speaker-slash-bold": 58458,
  "speaker-x-bold": 58460,
  "speedometer-bold": 61044,
  "sphere-bold": 61030,
  "spinner-bold": 58986,
  "spinner-ball-bold": 60968,
  "spinner-gap-bold": 58988,
  "spiral-bold": 59898,
  "split-horizontal-bold": 59506,
  "split-vertical-bold": 59510,
  "spotify-logo-bold": 58990,
  "spray-bottle-bold": 59364,
  "square-bold": 58462,
  "square-half-bold": 58466,
  "square-half-bottom-bold": 60182,
  "square-logo-bold": 59024,
  "square-split-horizontal-bold": 59504,
  "square-split-vertical-bold": 59508,
  "squares-four-bold": 58468,
  "stack-bold": 58470,
  "stack-minus-bold": 60916,
  "stack-overflow-logo-bold": 60280,
  "stack-plus-bold": 60918,
  "stack-simple-bold": 58472,
  "stairs-bold": 59628,
  "stamp-bold": 59976,
  "standard-definition-bold": 60048,
  "star-bold": 58474,
  "star-and-crescent-bold": 60660,
  "star-four-bold": 59044,
  "star-half-bold": 59146,
  "star-of-david-bold": 59550,
  "steam-logo-bold": 60116,
  "steering-wheel-bold": 59820,
  "steps-bold": 60606,
  "stethoscope-bold": 59370,
  "sticker-bold": 58796,
  "stool-bold": 59972,
  "stop-bold": 58476,
  "stop-circle-bold": 58478,
  "storefront-bold": 58480,
  "strategy-bold": 59962,
  "stripe-logo-bold": 59032,
  "student-bold": 59198,
  "subset-of-bold": 60864,
  "subset-proper-of-bold": 60854,
  "subtitles-bold": 57768,
  "subtitles-slash-bold": 57766,
  "subtract-bold": 60374,
  "subtract-square-bold": 60372,
  "subway-bold": 58520,
  "suitcase-bold": 58798,
  "suitcase-rolling-bold": 59824,
  "suitcase-simple-bold": 58800,
  "sun-bold": 58482,
  "sun-dim-bold": 58484,
  "sun-horizon-bold": 58806,
  "sunglasses-bold": 59414,
  "superset-of-bold": 60856,
  "superset-proper-of-bold": 60852,
  "swap-bold": 59452,
  "swatches-bold": 58808,
  "swimming-pool-bold": 60598,
  "sword-bold": 58810,
  "synagogue-bold": 60652,
  "syringe-bold": 59752,
  "t-shirt-bold": 58992,
  "table-bold": 58486,
  "tabs-bold": 59256,
  "tag-bold": 58488,
  "tag-chevron-bold": 58994,
  "tag-simple-bold": 58490,
  "target-bold": 58492,
  "taxi-bold": 59650,
  "tea-bag-bold": 59622,
  "telegram-logo-bold": 58812,
  "television-bold": 59220,
  "television-simple-bold": 60134,
  "tennis-ball-bold": 59168,
  "tent-bold": 59578,
  "terminal-bold": 58494,
  "terminal-window-bold": 60136,
  "test-tube-bold": 59296,
  "text-a-underline-bold": 60724,
  "text-aa-bold": 59118,
  "text-align-center-bold": 58496,
  "text-align-justify-bold": 58498,
  "text-align-left-bold": 58500,
  "text-align-right-bold": 58502,
  "text-b-bold, text-bolder-bold": 58814,
  "text-columns-bold": 60566,
  "text-h-bold": 59066,
  "text-h-five-bold": 59076,
  "text-h-four-bold": 59074,
  "text-h-one-bold": 59068,
  "text-h-six-bold": 59078,
  "text-h-three-bold": 59072,
  "text-h-two-bold": 59070,
  "text-indent-bold": 59934,
  "text-italic-bold": 58816,
  "text-outdent-bold": 59932,
  "text-strikethrough-bold": 58818,
  "text-subscript-bold": 60568,
  "text-superscript-bold": 60570,
  "text-t-bold": 58506,
  "text-t-slash-bold": 58504,
  "text-underline-bold": 58820,
  "textbox-bold": 60170,
  "thermometer-bold": 58822,
  "thermometer-cold-bold": 58824,
  "thermometer-hot-bold": 58826,
  "thermometer-simple-bold": 58828,
  "threads-logo-bold": 60830,
  "three-d-bold": 59994,
  "thumbs-down-bold": 58508,
  "thumbs-up-bold": 58510,
  "ticket-bold": 58512,
  "tidal-logo-bold": 60700,
  "tiktok-logo-bold": 60146,
  "tilde-bold": 60840,
  "timer-bold": 58514,
  "tip-jar-bold": 59362,
  "tipi-bold": 60720,
  "tire-bold": 60882,
  "toggle-left-bold": 58996,
  "toggle-right-bold": 58998,
  "toilet-bold": 59290,
  "toilet-paper-bold": 59292,
  "toolbox-bold": 60576,
  "tooth-bold": 59852,
  "tornado-bold": 59532,
  "tote-bold": 58516,
  "tote-simple-bold": 59000,
  "towel-bold": 60902,
  "tractor-bold": 60526,
  "trademark-bold": 59888,
  "trademark-registered-bold": 58356,
  "traffic-cone-bold": 59816,
  "traffic-sign-bold": 59002,
  "traffic-signal-bold": 59818,
  "train-bold": 58518,
  "train-regional-bold": 58526,
  "train-simple-bold": 58528,
  "tram-bold": 59884,
  "translate-bold": 58530,
  "trash-bold": 58534,
  "trash-simple-bold": 58536,
  "tray-bold": 58538,
  "tray-arrow-down-bold, archive-tray-bold": 57360,
  "tray-arrow-up-bold": 61010,
  "treasure-chest-bold": 60898,
  "tree-bold": 59098,
  "tree-evergreen-bold": 59100,
  "tree-palm-bold": 59674,
  "tree-structure-bold": 59004,
  "tree-view-bold": 61000,
  "trend-down-bold": 58540,
  "trend-up-bold": 58542,
  "triangle-bold": 58544,
  "triangle-dashed-bold": 58546,
  "trolley-bold": 58802,
  "trolley-suitcase-bold": 58804,
  "trophy-bold": 59006,
  "truck-bold": 58548,
  "truck-trailer-bold": 58550,
  "tumblr-logo-bold": 59604,
  "twitch-logo-bold": 58830,
  "twitter-logo-bold": 58554,
  "umbrella-bold": 59012,
  "umbrella-simple-bold": 59014,
  "union-bold": 60862,
  "unite-bold": 59518,
  "unite-square-bold": 59512,
  "upload-bold": 58558,
  "upload-simple-bold": 58560,
  "usb-bold": 59734,
  "user-bold": 58562,
  "user-check-bold": 60154,
  "user-circle-bold": 58564,
  "user-circle-check-bold": 60472,
  "user-circle-dashed-bold": 60470,
  "user-circle-gear-bold": 58566,
  "user-circle-minus-bold": 58568,
  "user-circle-plus-bold": 58570,
  "user-focus-bold": 59132,
  "user-gear-bold": 58572,
  "user-list-bold": 59196,
  "user-minus-bold": 58574,
  "user-plus-bold": 58576,
  "user-rectangle-bold": 58578,
  "user-sound-bold": 60584,
  "user-square-bold": 58580,
  "user-switch-bold": 59222,
  "users-bold": 58582,
  "users-four-bold": 59020,
  "users-three-bold": 59022,
  "van-bold": 59430,
  "vault-bold": 59246,
  "vector-three-bold": 61026,
  "vector-two-bold": 61028,
  "vibrate-bold": 58584,
  "video-bold": 59200,
  "video-camera-bold": 58586,
  "video-camera-slash-bold": 58588,
  "video-conference-bold": 60878,
  "vignette-bold": 60322,
  "vinyl-record-bold": 60588,
  "virtual-reality-bold": 59320,
  "virus-bold": 59350,
  "visor-bold": 60970,
  "voicemail-bold": 58590,
  "volleyball-bold": 59174,
  "wall-bold": 59016,
  "wallet-bold": 59018,
  "warehouse-bold": 60628,
  "warning-bold": 58592,
  "warning-circle-bold": 58594,
  "warning-diamond-bold": 59388,
  "warning-octagon-bold": 58596,
  "washing-machine-bold": 60904,
  "watch-bold": 58598,
  "wave-sawtooth-bold": 60060,
  "wave-sine-bold": 60058,
  "wave-square-bold": 60062,
  "wave-triangle-bold": 60064,
  "waveform-bold": 59394,
  "waveform-slash-bold": 59392,
  "waves-bold": 59102,
  "webcam-bold": 59826,
  "webcam-slash-bold": 60636,
  "webhooks-logo-bold": 60590,
  "wechat-logo-bold": 59602,
  "whatsapp-logo-bold": 58832,
  "wheelchair-bold": 58600,
  "wheelchair-motion-bold": 59546,
  "wifi-high-bold": 58602,
  "wifi-low-bold": 58604,
  "wifi-medium-bold": 58606,
  "wifi-none-bold": 58608,
  "wifi-slash-bold": 58610,
  "wifi-x-bold": 58612,
  "wind-bold": 58834,
  "windmill-bold": 59896,
  "windows-logo-bold": 59026,
  "wine-bold": 59058,
  "wrench-bold": 58836,
  "x-bold": 58614,
  "x-circle-bold": 58616,
  "x-logo-bold": 58556,
  "x-square-bold": 58618,
  "yarn-bold": 60826,
  "yin-yang-bold": 59690,
  "youtube-logo-bold": 58620
}